qmetro/__init__.py
qmetro/consts.py
qmetro/qtools.py
qmetro/utils.py
qmetro/bounds/__init__.py
qmetro/bounds/bounds.py
qmetro/iss_opt/__init__.py
qmetro/iss_opt/artnoise.py
qmetro/iss_opt/consts.py
qmetro/iss_opt/errors.py
qmetro/iss_opt/iss_config.py
qmetro/iss_opt/iss_warnings.py
qmetro/iss_opt/main.py
qmetro/iss_opt/optimize.py
qmetro/param_channel/__init__.py
qmetro/param_channel/creators.py
qmetro/param_channel/param_channel.py
qmetro/protocols/__init__.py
qmetro/protocols/errors.py
qmetro/protocols/iss.py
qmetro/protocols/mop.py
qmetro/protocols/other.py
qmetro/protocols/warnings.py
qmetro/qmtensor/__init__.py
qmetro/qmtensor/operations.py
qmetro/qmtensor/classes/__init__.py
qmetro/qmtensor/classes/tensors.py
qmetro/qmtensor/creators/__init__.py
qmetro/qmtensor/creators/single.py
qmetro/qmtensor/creators/structures.py
qmetro-1.1.1.dist-info/licenses/LICENSE
qmetro-1.1.1.dist-info/METADATA
qmetro-1.1.1.dist-info/WHEEL
qmetro-1.1.1.dist-info/top_level.txt
qmetro-1.1.1.dist-info/RECORD
