Metadata-Version: 2.4
Name: qmetro
Version: 1.1.1
Summary: A package that provides a set of tools for identifying optimal estimation protocols that maximize quantum Fisher information (QFI).
Home-page: https://github.com/pdulian/qmetro
Author: Piotr Dulian and Stanisław Kurdziałek
Author-email: p.dulian@cent.uw.edu.pl
License: GPLv3
Project-URL: Documentation, https://qmetro.readthedocs.io/en/latest/
Project-URL: Source, https://github.com/pdulian/qmetro
Project-URL: Article, https://arxiv.org/abs/2506.16524
Keywords: quantum metrology optimization physics
Requires-Python: >=3.10
License-File: LICENSE
Requires-Dist: numpy>=1.26.4
Requires-Dist: scipy>=1.14.1
Requires-Dist: cvxpy>=1.6.0
Requires-Dist: matplotlib>=3.10.0
Requires-Dist: networkx>=3.3
Requires-Dist: ncon
Dynamic: author
Dynamic: author-email
Dynamic: description
Dynamic: description-content-type
Dynamic: home-page
Dynamic: keywords
Dynamic: license
Dynamic: license-file
Dynamic: project-url
Dynamic: requires-dist
Dynamic: requires-python
Dynamic: summary
